[
    {
        "store_url": "https://www.yesglasses.com/",
        "coupon_code": "CLEARANCE"
    },
    {
        "store_url": "https://teamwarrior.com/",
        "coupon_code": "GIFTFREE"
    },
    {
        "store_url": "https://bluefinsupboards.com/special-offers/",
        "coupon_code": "DAY5SPECIALITY"
    },
    {
        "store_url": "https://www.directstoves.com/",
        "coupon_code": "AW50OFF20"
    },
    {
        "store_url": "https://www.directstoves.com/",
        "coupon_code": "AW40OFF20"
    },
    {
        "store_url": "https://www.directstoves.com/",
        "coupon_code": "AW20OFF20"
    },
    {
        "store_url": "https://www.direct-fireplaces.com/",
        "coupon_code": "AW50OFF20"
    },
    {
        "store_url": "https://www.direct-fireplaces.com/",
        "coupon_code": "AW20OFF20"
    },
    {
        "store_url": "https://www.direct-fireplaces.com/",
        "coupon_code": "AW40OFF20"
    },
    {
        "store_url": "https://goddiva.co.uk/collections/goddivas-top-picks",
        "coupon_code": "TRENDING40"
    },
    {
        "store_url": "https://www.kinguin.net/category/43324/hellcase-com-20-usd-wallet-card-code",
        "coupon_code": "JINGLE4"
    },
    {
        "store_url": "https://www.kinguin.net/category/43324/hellcase-com-20-usd-wallet-card-code",
        "coupon_code": "JINGLE4"
    },
    {
        "store_url": "https://www.prettylittlething.us/",
        "coupon_code": "USA8AFF"
    },
    {
        "store_url": "https://www.prettylittlething.us/",
        "coupon_code": "USA12NEW"
    },
    {
        "store_url": "https://www.letterfolk.com/",
        "coupon_code": "GIFTS"
    },
    {
        "store_url": "https://www.allbeauty.com/offers/daily-deals.list",
        "coupon_code": "SPARK10"
    },
    {
        "store_url": "https://www.appleyardflowers.com/christmas-gifts/wreaths-and-trees",
        "coupon_code": "APMT20"
    },
    {
        "store_url": "https://www.prettylittlething.com/",
        "coupon_code": "UK8AFF"
    },
    {
        "store_url": "https://www.tigersheds.com/wooden-playhouses/",
        "coupon_code": "SVPLAY10"
    },
    {
        "store_url": "https://www.allbeauty.com/offers/daily-deals.list",
        "coupon_code": "SPARK10"
    },
    {
        "store_url": "https://www.scribbler.com/",
        "coupon_code": "HOLLY10"
    },
    {
        "store_url": "https://www.scribbler.com/",
        "coupon_code": "GIFTMAS20"
    },
    {
        "store_url": "https://www.peets.com/collections/peets-gifts-sale",
        "coupon_code": "GIFT"
    },
    {
        "store_url": "https://www.dietdirect.com/30-off-sale/",
        "coupon_code": "30SAVINGS"
    },
    {
        "store_url": "https://www.dietdirect.com/shop-plans.html",
        "coupon_code": "DIETSAVE"
    },
    {
        "store_url": "https://www.yesglasses.com/winter-clearance-sale",
        "coupon_code": "CLEARANCE"
    },
    {
        "store_url": "https://www.petcaresupplies.com/bravecto-for-medium-dogs-22-44-lbs-green-pack-101.aspx?coupon_no=take15",
        "coupon_code": "TAKE15"
    },
    {
        "store_url": "https://www.jurllyshe.com/",
        "coupon_code": "Dec40"
    },
    {
        "store_url": "https://www.jurllyshe.com/",
        "coupon_code": "Dec30"
    },
    {
        "store_url": "https://www.avis.com/en/home",
        "coupon_code": ""
    },
    {
        "store_url": "https://www.jacamo.co.uk/shop/c/occasionwear?skimoffer=2123933",
        "coupon_code": "SMART"
    },
    {
        "store_url": "https://www.belkin.com/products/?skimoffer=2334560",
        "coupon_code": "GIFT23"
    },
    {
        "store_url": "https://www.famous-smoke.com/promo/AFFNOVFS23?coupon=FREESHIP23NOV&skimoffer=2382299",
        "coupon_code": "2338676W04DEC"
    },
    {
        "store_url": "https://www.famous-smoke.com/promo/AFFNOVFS23?coupon=FREESHIP23NOV&skimoffer=2382307",
        "coupon_code": "2349143W04DEC"
    },
    {
        "store_url": "https://www.famous-smoke.com/promo/AFFNOVFS23?coupon=FREESHIP23NOV&skimoffer=2382312",
        "coupon_code": "2315093W04DEC"
    },
    {
        "store_url": "https://www.famous-smoke.com/promo/AFFNOVFS23?coupon=FREESHIP23NOV&skimoffer=2382320",
        "coupon_code": "2372888W04DEC"
    },
    {
        "store_url": "https://www.famous-smoke.com/promo/AFFNOVFS23?coupon=FREESHIP23NOV&skimoffer=2382336",
        "coupon_code": "2368208W04DEC"
    },
    {
        "store_url": "https://www.famous-smoke.com/promo/AFFNOVFS23?coupon=FREESHIP23NOV&skimoffer=2382338",
        "coupon_code": "2368975W04DEC"
    },
    {
        "store_url": "https://www.lovesac.com/?skimoffer=2431686",
        "coupon_code": ""
    },
    {
        "store_url": "https://www.sagefinds.com/Default.aspx?stackpromo=SF120423B&skimoffer=2432725",
        "coupon_code": ""
    },
    {
        "store_url": "https://www.chadwicks.com/Default.aspx?stackpromo=HD120423B&skimoffer=2432756",
        "coupon_code": ""
    },
    {
        "store_url": "https://www.sockpanda.com?skimoffer=2432971",
        "coupon_code": "BestEver25"
    },
    {
        "store_url": "https://www.burtsbeesbaby.com/?skimoffer=2433163",
        "coupon_code": ""
    },
    {
        "store_url": "https://www.proozy.com/a/bundles/penguin-mens-fleece-jogger-+-penguin-mens-henley-long-sleeve-shirt-8gm3?sscid=c1k7_3kgwr&sv_campaign_id=314743&skimoffer=2433963",
        "coupon_code": "PZY2MPD-FS"
    },
    {
        "store_url": "https://www.proozy.com/products/canada-weather-gear-womens-unlined-flannel?sscid=c1k7_3kgxc&sv_campaign_id=314743&skimoffer=2433965",
        "coupon_code": "PZYWCWGF-FS"
    },
    {
        "store_url": "https://www.proozy.com/a/bundles/90-degrees-by-reflex-womens-snow-wash-drop-armhole-tank-top-+-hurley-womens-tight-legging-8i9a?sscid=c1k7_3kgxr&sv_campaign_id=314743&skimoffer=2433966",
        "coupon_code": "PZYWNDB-FS"
    },
    {
        "store_url": "https://www.proozy.com/products/hurley-womens-city-stretch-jogger?sscid=c1k7_3kgxz&sv_campaign_id=314743&skimoffer=2433967",
        "coupon_code": "PZYWCSJ-FS"
    },
    {
        "store_url": "https://www.proozy.com/products/eddie-bauer-kids-2-piece-pajama-set?sscid=c1k7_3kgyd&sv_campaign_id=314743&skimoffer=2433968",
        "coupon_code": "PZYEB2PS-FS"
    },
    {
        "store_url": "https://www.proozy.com/products/life-is-good-mens-3pk-super-soft-boxer-brief?sscid=c1k7_3kgyn&sv_campaign_id=314743&skimoffer=2433969",
        "coupon_code": "PZY3PMB-FS"
    },
    {
        "store_url": "https://www.sportsmansguide.com/?skimoffer=2434207",
        "coupon_code": "SG4339"
    },
    {
        "store_url": "https://www.staples.com/laptops-Deals/cat_CL167289/00792?skimoffer=2434212",
        "coupon_code": ""
    },
    {
        "store_url": "https://www.staples.com/hp-smart-tank-5000-inkjet-all-in-one-printer-5d1b6a-b1h/product_24571320?skimoffer=2434213",
        "coupon_code": ""
    },
    {
        "store_url": "https://www.staples.com/services/printing/holiday-photo-gifts/?skimoffer=2434214",
        "coupon_code": "80323"
    },
    {
        "store_url": "https://www.strivectin.com/?skimoffer=2434451",
        "coupon_code": ""
    },
    {
        "store_url": "https://www.fifthsun.com?sscid=c1k7_3kevk&skimoffer=2434545",
        "coupon_code": "XMAS"
    },
    {
        "store_url": "https://www.designbyhumans.com/?sscid=c1k7_3kexl&skimoffer=2434547",
        "coupon_code": "SANTA"
    },
    {
        "store_url": "https://www.newchapter.com/shop-all-products/?skimoffer=2434680",
        "coupon_code": "DEAL1MULTIS"
    },
    {
        "store_url": "https://www.online4baby.com/big-baby-event?skimoffer=2435054",
        "coupon_code": ""
    },
    {
        "store_url": "https://www.scribbler.com/?skimoffer=2435084",
        "coupon_code": "GIFTMAS20"
    },
    {
        "store_url": "https://www.scribbler.com/?skimoffer=2435085",
        "coupon_code": "HOLLY10"
    },
    {
        "store_url": "https://www.fragrancedirect.co.uk/offers/brands-on-offer.list?skimoffer=2435250",
        "coupon_code": "EXTRA10"
    },
    {
        "store_url": "https://www.gadventures.com/travel-styles/cruising/expedition-cruises/antarctica/?skimoffer=2435279",
        "coupon_code": ""
    },
    {
        "store_url": "https://www.perriconemd.com/holiday/12-days-of-customer-favorites/preview.list?skimoffer=2435591",
        "coupon_code": ""
    },
    {
        "store_url": "https://www.perriconemd.com/holiday/12-days-of-customer-favorites/preview.list?skimoffer=2435593",
        "coupon_code": ""
    },
    {
        "store_url": "https://www.fragrancedirect.co.uk/offers/sitewide.list?skimoffer=2435675",
        "coupon_code": "FLASH12"
    },
    {
        "store_url": "https://www.online4baby.com/all/Huffy/375?skimoffer=2436251",
        "coupon_code": ""
    },
    {
        "store_url": "https://www.online4baby.com/baby-play-essentials?skimoffer=2436252",
        "coupon_code": ""
    },
    {
        "store_url": "https://www.lights4fun.co.uk/collections/12-days-of-christmas-deals?skimoffer=2436421",
        "coupon_code": ""
    },
    {
        "store_url": "https://lilycharmed.com/?skimoffer=2436977",
        "coupon_code": ""
    },
    {
        "store_url": "https://www.fishingtackleandbait.co.uk/en/gb/Christmas-Fishing-Clothing-Deals/cpl-511.aspx?skimoffer=2438088",
        "coupon_code": ""
    },
    {
        "store_url": "https://www.fishingtackleandbait.co.uk/en/gb/Christmas-Carp-Fishing-Deals/cpl-516.aspx?skimoffer=2438089",
        "coupon_code": ""
    },
    {
        "store_url": "https://www.fishingtackleandbait.co.uk/en/gb/Christmas-Sea-Fishing-Deals/cpl-515.aspx?skimoffer=2438090",
        "coupon_code": ""
    },
    {
        "store_url": "https://www.fishingtackleandbait.co.uk/en/gb/Christmas-Fly-Fishing-Deals/cpl-514.aspx?skimoffer=2438091",
        "coupon_code": ""
    },
    {
        "store_url": "https://www.fishingtackleandbait.co.uk/en/gb/Christmas-Pike-Fishing-Deals/cpl-513.aspx?skimoffer=2438092",
        "coupon_code": ""
    },
    {
        "store_url": "https://www.fishingtackleandbait.co.uk/en/gb/Christmas-Coarse-Fishing-Deals/cpl-512.aspx?skimoffer=2438093",
        "coupon_code": ""
    },
    {
        "store_url": "https://www.fishingtackleandbait.co.uk/en/Christmas-Sale/cc-79.aspx?skimoffer=2438094",
        "coupon_code": ""
    },
    {
        "store_url": "https://www.directstoves.com/?skimoffer=2438205",
        "coupon_code": "AW50OFF20"
    },
    {
        "store_url": "https://www.directstoves.com/?skimoffer=2438206",
        "coupon_code": "AW40OFF20"
    },
    {
        "store_url": "https://www.directstoves.com/?skimoffer=2438207",
        "coupon_code": "AW20OFF20"
    },
    {
        "store_url": "https://www.direct-fireplaces.com/?skimoffer=2438216",
        "coupon_code": "AW50OFF20"
    },
    {
        "store_url": "https://www.direct-fireplaces.com/?skimoffer=2438217",
        "coupon_code": "AW40OFF20"
    },
    {
        "store_url": "https://www.direct-fireplaces.com/?skimoffer=2438218",
        "coupon_code": "AW20OFF20"
    },
    {
        "store_url": "https://socksnob.co.uk/?skimoffer=2439438",
        "coupon_code": "SOXFORCRIMBO15"
    },
    {
        "store_url": "https://socksnob.co.uk/?skimoffer=2439439",
        "coupon_code": "SOXALLDAY"
    },
    {
        "store_url": "https://www.jurllyshe.com?sscid=c1k7_3kdmk&skimoffer=2439757",
        "coupon_code": "Dec30"
    },
    {
        "store_url": "https://www.jurllyshe.com?sscid=c1k7_3kdmw&skimoffer=2439758",
        "coupon_code": "Dec40"
    },
    {
        "store_url": "https://egoshoes.com//flats/womens-slippers.html?skimoffer=2439778",
        "coupon_code": ""
    },
    {
        "store_url": "https://egoshoes.com/unholy.html?skimoffer=2439779",
        "coupon_code": ""
    },
    {
        "store_url": "https://egoshoes.com/sub-zero.html?skimoffer=2439780",
        "coupon_code": ""
    },
    {
        "store_url": "https://www.penshop.co.uk/pens/montblanc?skimoffer=2439794",
        "coupon_code": "MBPEN10"
    },
    {
        "store_url": "https://www.angara.com/ca-en/c/jewellery?skimoffer=2439829",
        "coupon_code": ""
    },
    {
        "store_url": "https://kitbox.co/collections/black-friday-2023-highlights/products/tyr-cxt-1-trainer-white-black-multi?skimoffer=2439835",
        "coupon_code": ""
    },
    {
        "store_url": "https://kitbox.co/collections/black-friday-2023-highlights/products/tyr-rd1-runner-white-orange?skimoffer=2439836",
        "coupon_code": ""
    },
    {
        "store_url": "https://kitbox.co/collections/black-friday-2023-highlights/products/victory-grips-mens-leather-3-full-coverage-gymnastic-grips?skimoffer=2439837",
        "coupon_code": ""
    },
    {
        "store_url": "https://kitbox.co/collections/black-friday-2023-highlights/products/tyr-l1-lifter-weightlifting-shoe?skimoffer=2439838",
        "coupon_code": ""
    },
    {
        "store_url": "https://kitbox.co/collections/black-friday-2023-highlights/products/inov8-f-lite-245-training-shoes-white-black-multi?skimoffer=2439839",
        "coupon_code": ""
    },
    {
        "store_url": "https://www.angara.com/ca-en/c/jewellery?skimoffer=2439840",
        "coupon_code": "AF122EXTRA"
    },
    {
        "store_url": "https://technextday.co.uk/product/be-quiet-850w-pure-power-12-m-psu-fully-modular-80-gold-atx-3-0-pcie-5-0-power-supply/?skimoffer=2439882",
        "coupon_code": ""
    },
    {
        "store_url": "https://technextday.co.uk/product/asus-rog-ryuo-240mm-liquid-cpu-cooler-2-x-12cm-pwm-fan-full-colour-oled-display-rgb/?skimoffer=2439883",
        "coupon_code": ""
    },
    {
        "store_url": "https://technextday.co.uk/product/asrock-intel-z690-pro-rs-atx-ddr4-motherboard/?skimoffer=2439885",
        "coupon_code": ""
    }
]